MANIFEST.in
README.md
requirements.txt
setup.py
django_helpers_jieter.egg-info/PKG-INFO
django_helpers_jieter.egg-info/SOURCES.txt
django_helpers_jieter.egg-info/dependency_links.txt
django_helpers_jieter.egg-info/not-zip-safe
django_helpers_jieter.egg-info/requires.txt
django_helpers_jieter.egg-info/top_level.txt
helpers/__init__.py
helpers/admin.py
helpers/codestyle.py
helpers/containers.py
helpers/exception.py
helpers/geo.py
helpers/http.py
helpers/models.py
helpers/pdf.py
helpers/statistics.py
helpers/time.py
helpers/util.py
helpers/views.py
helpers/templates/admin/readonly_view.html
helpers/templates/helpers/table.html
helpers/templatetags/__init__.py
helpers/templatetags/analytics.py
helpers/templatetags/paginator.py