Metadata-Version: 1.1
Name: django-helpers-jieter
Version: 0.0.23
Summary: Some Django helpers I share between my projects
Home-page: https://github.com/jieter/django-helpers
Author: Jan Pieter Waagmeester
Author-email: jieter@jieter.nl
License: MIT
Keywords: django helpers
Platform: UNKNOWN
Classifier: Programming Language :: Python :: 2.7
Classifier: Operating System :: OS Independent
Classifier: Topic :: Software Development :: Libraries
Classifier: Topic :: Utilities
Classifier: Environment :: Web Environment
Classifier: Framework :: Django
